{
  "$schema": "https://mintlify.com/schema.json",
  "name": "Surfer",
  "logo": {
    "dark": "/logo/dark.svg",
    "light": "/logo/light.svg"
  },
  "favicon": "/favicon.svg",
  "colors": {
    "primary": "#0d7091",
    "light": "#07b3ca",
    "dark": "#0d7091",
    "anchors": {
      "from": "#0d7091",
      "to": "#07b3ca"
    }
  },
  "topbarLinks": [
    {
      "name": "Support",
      "url": "mailto:hi@mintlify.com"
    }
  ],
  "topbarCtaButton": {
    "name": "Dashboard",
    "url": "https://dashboard.mintlify.com"
  },
  "tabs": [
    {
      "name": "API Reference",
      "url": "api-reference"
    }
  ],
  "anchors": [
    {
      "name": "Documentation",
      "icon": "book-open-cover",
      "url": "https://mintlify.com/docs"
    },
    {
      "name": "Community",
      "icon": "slack",
      "url": "https://mintlify.com/community"
    },
    {
      "name": "Blog",
      "icon": "newspaper",
      "url": "https://mintlify.com/blog"
    }
  ],
  "navigation": [
    {
      "group": "Get Started",
      "pages": [
        "introduction",
        "quickstart",
        "development"
      ]
    },
    {
      "group": "Essentials",
      "pages": [
        "essentials/markdown",
        "essentials/code",
        "essentials/images",
        "essentials/settings",
        "essentials/navigation",
        "essentials/reusable-snippets"
      ]
    },
    {
      "group": "API Documentation",
      "pages": [
        "api-reference/introduction"
      ]
    },
    {
      "group": "Endpoint Examples",
      "pages": [
        "api-reference/endpoint/check-if-server-is-up",
        "check-if-server-is-up",
        "healthcheck-endpoint",
        "start-a-new-session",
        "end-a-session",
        "get-current-dom-representation",
        "update-current-dom-representation",
        "get-current-tools",
        "update-current-tools",
        "get-current-markdown",
        "update-current-markdown",
        "get-current-url",
        "update-current-url",
        "get-all-current-sessions",
        "use-a-tool",
        "clear-all-sessions"
      ]
    }
  ],
  "footerSocials": {
    "x": "https://x.com/mintlify",
    "github": "https://github.com/mintlify",
    "linkedin": "https://www.linkedin.com/company/mintsearch"
  }
}